buildc/__init__.py
buildc/__main__.py
buildc/_version.py
buildc/cli.py
buildc/config.json
buildc/rootfs.py
buildc/test_version.py
buildc-0.0.2.dist-info/LICENSE
buildc-0.0.2.dist-info/METADATA
buildc-0.0.2.dist-info/WHEEL
buildc-0.0.2.dist-info/entry_points.txt
buildc-0.0.2.dist-info/top_level.txt
buildc-0.0.2.dist-info/RECORD
