Metadata-Version: 2.1
Name: buildc
Version: 0.0.2
Summary: Report files opened while executing a command
Home-page: https://github.com/joaompinto/buildc
Author: João Pinto
Author-email: joao.pinto@vshn.ch
License: BSD-3
Platform: UNKNOWN
Requires-Dist: filetrace
Requires-Dist: file-magic
